clarasr/__init__.py
clarasr/main.py
clarasr-0.1.6.dist-info/METADATA
clarasr-0.1.6.dist-info/WHEEL
clarasr-0.1.6.dist-info/top_level.txt
clarasr-0.1.6.dist-info/RECORD
