Metadata-Version: 2.1
Name: clarasr
Version: 0.1.6
Summary: A Python package for speech recognition. 
Home-page: https://github.com/kikostudios/clarasr
Author: Krystof KikoStudios Hrdy
Author-email: your.email@example.com
Classifier: Programming Language :: Python :: 3
Classifier: License :: OSI Approved :: MIT License
Classifier: Operating System :: OS Independent
Requires-Python: >=3.6
Requires-Dist: SpeechRecognition>=3.10.0
Requires-Dist: PyAudio>=0.2.13
Requires-Dist: numpy>=1.24.0
Requires-Dist: torch>=2.0.0
Requires-Dist: requests>=2.31.0
